OntoAnon/__init__.py
OntoAnon/__main__.py
OntoAnon/anonymization.py
OntoAnon-1.0.0.dist-info/LICENSE
OntoAnon-1.0.0.dist-info/METADATA
OntoAnon-1.0.0.dist-info/WHEEL
OntoAnon-1.0.0.dist-info/entry_points.txt
OntoAnon-1.0.0.dist-info/top_level.txt
OntoAnon-1.0.0.dist-info/RECORD
