Metadata-Version: 2.1
Name: OntoAnon
Version: 1.0.0
Summary: A Structural Anonymizer for Ontologies
Author-email: Achim Reiz <achim.reiz@uni-rostock.de>
Project-URL: Homepage, https://github.com/Uni-Rostock-Win/OntoAnon
Project-URL: Bug Tracker, https://github.com/Uni-Rostock-Win/OntoAnon/issues
Classifier: Programming Language :: Python :: 3
Classifier: License :: OSI Approved :: MIT License
Classifier: Operating System :: OS Independent
Requires-Python: >=3.7
License-File: LICENSE
Requires-Dist: rdflib
